README.md
setup.py
mdabrowska_hello_world.egg-info/PKG-INFO
mdabrowska_hello_world.egg-info/SOURCES.txt
mdabrowska_hello_world.egg-info/dependency_links.txt
mdabrowska_hello_world.egg-info/top_level.txt
sample_package/__init__.py
sample_package/sample.py